znakes/__about__.py
znakes/__init__.py
znakes/curves.py
znakes/eddsa.py
znakes/fields.py
znakes/numbertheory.py
znakes/utils.py
znakes/gadgets/__init__.py
znakes/gadgets/pedersenHasher.py
znakes-0.1.1.dist-info/METADATA
znakes-0.1.1.dist-info/WHEEL
znakes-0.1.1.dist-info/licenses/LICENSE
znakes-0.1.1.dist-info/RECORD
