Metadata-Version: 2.1
Name: ZnaKes
Version: 0.1.1
Summary: A python client library to easily generate arguments for zero-knowledge proofs (ZKPs)
Project-URL: Homepage, https://github.com/ZK-Plus/ZnaKes
Project-URL: Issues, https://github.com/ZK-Plus/ZnaKes/issues
Author-email: alvaro-alonso <aa@ise.tu-berlin.de>
License-File: LICENSE
Classifier: Intended Audience :: Developers
Classifier: License :: OSI Approved :: GNU General Public License v3 (GPLv3)
Classifier: Operating System :: OS Independent
Classifier: Programming Language :: Python :: 3
Classifier: Topic :: Education
Classifier: Topic :: Security :: Cryptography
Requires-Python: >=3.8
